{
  "parent": "minecraft:item/generated",
  "overrides": [
    {
      "model": "malum:item/ritual_shard_dim",
      "predicate": {
        "minecraft:stored_ritual": 2.0
      }
    },
    {
      "model": "malum:item/ritual_shard_vague",
      "predicate": {
        "minecraft:stored_ritual": 3.0
      }
    },
    {
      "model": "malum:item/ritual_shard_bright",
      "predicate": {
        "minecraft:stored_ritual": 4.0
      }
    },
    {
      "model": "malum:item/ritual_shard_vivid",
      "predicate": {
        "minecraft:stored_ritual": 5.0
      }
    },
    {
      "model": "malum:item/ritual_shard_radiant",
      "predicate": {
        "minecraft:stored_ritual": 6.0
      }
    }
  ],
  "textures": {
    "layer0": "malum:item/ritual_shard_faded"
  }
}