{
  "parent": "minecraft:recipes/root",
  "criteria": {
    "has_hex_ash": {
      "conditions": {
        "items": [
          {
            "items": [
              "malum:hex_ash"
            ]
          }
        ]
      },
      "trigger": "minecraft:inventory_changed"
    },
    "has_the_recipe": {
      "conditions": {
        "recipe": "malum:spectral_lens"
      },
      "trigger": "minecraft:recipe_unlocked"
    }
  },
  "requirements": [
    [
      "has_hex_ash",
      "has_the_recipe"
    ]
  ],
  "rewards": {
    "recipes": [
      "malum:spectral_lens"
    ]
  },
  "sends_telemetry_event": false
}