{
  "variants": {
    "blight_type=grounded_roots,facing=east": {
      "model": "malum:block/clinging_blight_grounded_roots",
      "y": 90
    },
    "blight_type=grounded_roots,facing=north": {
      "model": "malum:block/clinging_blight_grounded_roots"
    },
    "blight_type=grounded_roots,facing=south": {
      "model": "malum:block/clinging_blight_grounded_roots",
      "y": 180
    },
    "blight_type=grounded_roots,facing=west": {
      "model": "malum:block/clinging_blight_grounded_roots",
      "y": 270
    },
    "blight_type=hanging_blight,facing=east": {
      "model": "malum:block/clinging_blight_hanging_blight",
      "y": 90
    },
    "blight_type=hanging_blight,facing=north": {
      "model": "malum:block/clinging_blight_hanging_blight"
    },
    "blight_type=hanging_blight,facing=south": {
      "model": "malum:block/clinging_blight_hanging_blight",
      "y": 180
    },
    "blight_type=hanging_blight,facing=west": {
      "model": "malum:block/clinging_blight_hanging_blight",
      "y": 270
    },
    "blight_type=hanging_blight_connection,facing=east": {
      "model": "malum:block/clinging_blight_hanging_blight_connection",
      "y": 90
    },
    "blight_type=hanging_blight_connection,facing=north": {
      "model": "malum:block/clinging_blight_hanging_blight_connection"
    },
    "blight_type=hanging_blight_connection,facing=south": {
      "model": "malum:block/clinging_blight_hanging_blight_connection",
      "y": 180
    },
    "blight_type=hanging_blight_connection,facing=west": {
      "model": "malum:block/clinging_blight_hanging_blight_connection",
      "y": 270
    },
    "blight_type=hanging_roots,facing=east": {
      "model": "malum:block/clinging_blight_hanging_roots",
      "y": 90
    },
    "blight_type=hanging_roots,facing=north": {
      "model": "malum:block/clinging_blight_hanging_roots"
    },
    "blight_type=hanging_roots,facing=south": {
      "model": "malum:block/clinging_blight_hanging_roots",
      "y": 180
    },
    "blight_type=hanging_roots,facing=west": {
      "model": "malum:block/clinging_blight_hanging_roots",
      "y": 270
    },
    "blight_type=rooted_blight,facing=east": {
      "model": "malum:block/clinging_blight_rooted_blight",
      "y": 90
    },
    "blight_type=rooted_blight,facing=north": {
      "model": "malum:block/clinging_blight_rooted_blight"
    },
    "blight_type=rooted_blight,facing=south": {
      "model": "malum:block/clinging_blight_rooted_blight",
      "y": 180
    },
    "blight_type=rooted_blight,facing=west": {
      "model": "malum:block/clinging_blight_rooted_blight",
      "y": 270
    },
    "blight_type=soulwood_spike,facing=east": {
      "model": "malum:block/clinging_blight_soulwood_spike",
      "y": 90
    },
    "blight_type=soulwood_spike,facing=north": {
      "model": "malum:block/clinging_blight_soulwood_spike"
    },
    "blight_type=soulwood_spike,facing=south": {
      "model": "malum:block/clinging_blight_soulwood_spike",
      "y": 180
    },
    "blight_type=soulwood_spike,facing=west": {
      "model": "malum:block/clinging_blight_soulwood_spike",
      "y": 270
    }
  }
}